README.md
setup.py
quan_chem_kit.egg-info/PKG-INFO
quan_chem_kit.egg-info/SOURCES.txt
quan_chem_kit.egg-info/dependency_links.txt
quan_chem_kit.egg-info/requires.txt
quan_chem_kit.egg-info/top_level.txt
quan_chem_kit/chem_struct/__init__.py
quan_chem_kit/chem_struct/mol.py
quan_chem_kit/gaussian_kit/__init__.py