Metadata-Version: 2.1
Name: quan-chem-kit
Version: 0.0.1
Summary: A toolset for quantum chemistry
Home-page: https://github.com/zbc0315/quan_chem_kit
Author: zhang
Author-email: zhangbc0315@outlook.com
Classifier: Programming Language :: Python :: 3
Classifier: License :: OSI Approved :: MIT License
Classifier: Operating System :: OS Independent
Requires-Python: >=3.7
